LICENSE
README.md
grammar/postgres.ebnf
squel/__init__.py
squel/app.py
squel/cli.py
squel/grammar.py
squel/indenter.py
squel/parser.py
squel/transformer.py
squel/tree.py
squel/version.py
squel-1.0.0.dist-info/LICENSE
squel-1.0.0.dist-info/METADATA
squel-1.0.0.dist-info/WHEEL
squel-1.0.0.dist-info/entry_points.txt
squel-1.0.0.dist-info/RECORD
