Metadata-Version: 2.1
Name: squel
Version: 1.0.0
Summary: SQL parsing, done right
Home-page: https://github.com/nomorepanic/squel
License: MIT
Author: nomorepanic
Author-email: nomorepanic@nomorepanic.me
Requires-Python: >=3.11,<4.0
Classifier: License :: OSI Approved :: MIT License
Classifier: Programming Language :: Python :: 3
Classifier: Programming Language :: Python :: 3.11
Classifier: Programming Language :: Python :: 3.12
Requires-Dist: click (>=6.7)
Requires-Dist: lark-parser (>=0.6.4)
Project-URL: Repository, https://github.com/nomorepanic/squel
